setup.cfg
setup.py
./__init__.py
./opportunity.py
./opportunity.xml
./tryton.cfg
./tests/__init__.py
./tests/test_sale_opportunity.py
./tests/test_view_depends.py
./view/opportunity_form.xml
./view/opportunity_incoterm_form.xml
./view/opportunity_incoterm_tree.xml
openlabs_incoterm_sale_opportunity.egg-info/PKG-INFO
openlabs_incoterm_sale_opportunity.egg-info/SOURCES.txt
openlabs_incoterm_sale_opportunity.egg-info/dependency_links.txt
openlabs_incoterm_sale_opportunity.egg-info/entry_points.txt
openlabs_incoterm_sale_opportunity.egg-info/not-zip-safe
openlabs_incoterm_sale_opportunity.egg-info/requires.txt
openlabs_incoterm_sale_opportunity.egg-info/top_level.txt