Metadata-Version: 1.1
Name: openlabs-incoterm-sale-opportunity
Version: 3.0.1.0dev1
Summary: Intercom Sale Opportunity Module for Tryton
Home-page: UNKNOWN
Author: Openlabs Technologies & Consulting (P) Limited
Author-email: info@openlabs.co.in
License: UNKNOWN
Platform: UNKNOWN
Classifier: Development Status :: 4 - Beta
Classifier: Environment :: Plugins
Classifier: Intended Audience :: Developers
Classifier: Natural Language :: English
Classifier: Operating System :: OS Independent
Classifier: Programming Language :: Python
Classifier: Framework :: Tryton
Classifier: Topic :: Office/Business
